fuconv/__init__.py
fuconv/__main__.py
fuconv-0.0.2.dist-info/METADATA
fuconv-0.0.2.dist-info/WHEEL
fuconv-0.0.2.dist-info/entry_points.txt
fuconv-0.0.2.dist-info/top_level.txt
fuconv-0.0.2.dist-info/RECORD
