Metadata-Version: 2.1
Name: fuconv
Version: 0.0.2
Summary: uint and hex values converter for solidity CTFs
Home-page: https://github.com/root-tanishq/fuconv
Author: Tanishq Rathore
License: MIT
Platform: UNKNOWN
Classifier: Programming Language :: Python :: 3
